<?xml version='1.0' encoding='UTF-8'?>
<annotation>
  <filename>masks_150528_frame1364.png</filename>
  <size>
    <width>966</width>
    <height>1296</height>
  </size>
  <object>
    <name>weed</name>
    <label>1</label>
    <bndbox>
      <xmin>0</xmin>
      <xmax>14</xmax>
      <ymin>553</ymin>
      <ymax>581</ymax>
    </bndbox>
  </object>
  <object>
    <name>crop</name>
    <label>0</label>
    <bndbox>
      <xmin>0</xmin>
      <xmax>97</xmax>
      <ymin>1047</ymin>
      <ymax>1182</ymax>
    </bndbox>
  </object>
  <object>
    <name>weed</name>
    <label>1</label>
    <bndbox>
      <xmin>50</xmin>
      <xmax>81</xmax>
      <ymin>690</ymin>
      <ymax>712</ymax>
    </bndbox>
  </object>
  <object>
    <name>crop</name>
    <label>0</label>
    <bndbox>
      <xmin>205</xmin>
      <xmax>656</xmax>
      <ymin>840</ymin>
      <ymax>1284</ymax>
    </bndbox>
  </object>
  <object>
    <name>weed</name>
    <label>1</label>
    <bndbox>
      <xmin>209</xmin>
      <xmax>330</xmax>
      <ymin>431</ymin>
      <ymax>506</ymax>
    </bndbox>
  </object>
  <object>
    <name>weed</name>
    <label>1</label>
    <bndbox>
      <xmin>486</xmin>
      <xmax>556</xmax>
      <ymin>515</ymin>
      <ymax>585</ymax>
    </bndbox>
  </object>
  <object>
    <name>weed</name>
    <label>1</label>
    <bndbox>
      <xmin>520</xmin>
      <xmax>544</xmax>
      <ymin>562</ymin>
      <ymax>581</ymax>
    </bndbox>
  </object>
</annotation>
